processout/__init__.py
processout/activity.py
processout/addon.py
processout/alternativemerchantcertificate.py
processout/apirequest.py
processout/apiversion.py
processout/applepayalternativemerchantcertificates.py
processout/balance.py
processout/balances.py
processout/card.py
processout/cardinformation.py
processout/categoryerrorcodes.py
processout/client.py
processout/coupon.py
processout/customer.py
processout/customeraction.py
processout/customerphone.py
processout/discount.py
processout/dunningaction.py
processout/errorcodes.py
processout/event.py
processout/gateway.py
processout/gatewayconfiguration.py
processout/gatewayrequest.py
processout/invoice.py
processout/invoicebilling.py
processout/invoicedetail.py
processout/invoicedevice.py
processout/invoiceexternalfraudtools.py
processout/invoicerisk.py
processout/invoiceshipping.py
processout/invoiceshippingphone.py
processout/invoicesprocessnativepaymentresponse.py
processout/invoicetax.py
processout/nativeapmparameterdefinition.py
processout/nativeapmparametervalue.py
processout/nativeapmparametervaluedefinition.py
processout/nativeapmrequest.py
processout/nativeapmresponse.py
processout/nativeapmtransactiondetails.py
processout/nativeapmtransactiondetailsgateway.py
processout/nativeapmtransactiondetailsinvoice.py
processout/paymentdatanetworkauthentication.py
processout/paymentdatathreedsauthentication.py
processout/paymentdatathreedsrequest.py
processout/payout.py
processout/payoutitem.py
processout/plan.py
processout/product.py
processout/project.py
processout/projectsftpsettings.py
processout/refund.py
processout/subscription.py
processout/threeds.py
processout/token.py
processout/transaction.py
processout/transactionoperation.py
processout/unsupportedfeaturebypass.py
processout/webhook.py
processout/webhookendpoint.py
processout/errors/__init__.py
processout/errors/authenticationerror.py
processout/errors/genericerror.py
processout/errors/internalerror.py
processout/errors/notfounderror.py
processout-6.30.0.dist-info/LICENSE
processout-6.30.0.dist-info/METADATA
processout-6.30.0.dist-info/WHEEL
processout-6.30.0.dist-info/top_level.txt
processout-6.30.0.dist-info/RECORD
