Metadata-Version: 2.1
Name: processout
Version: 6.30.0
Summary: ProcessOut API bindings.
Home-page: https://github.com/processout/processout-python
Download-URL: https://github.com/processout/processout-python/tarball/6.30.0
Author: ProcessOut
Author-email: hi@processout.com
Keywords: ProcessOut,api,bindings
License-File: LICENSE
